README.md
setup.py
imdb_films_scraper/__init__.py
imdb_films_scraper/dataframing.py
imdb_films_scraper/films.py
imdb_films_scraper/main.py
imdb_films_scraper/movie_class.py
imdb_films_scraper/related_films.py
imdb_films_scraper.egg-info/PKG-INFO
imdb_films_scraper.egg-info/SOURCES.txt
imdb_films_scraper.egg-info/dependency_links.txt
imdb_films_scraper.egg-info/requires.txt
imdb_films_scraper.egg-info/top_level.txt